discovery/__init__.py
discovery/discover.py
discovery/discovery_service.py
discovery/interfaces.py
pyros_discovery-1.1.1.dist-info/LICENSE
pyros_discovery-1.1.1.dist-info/METADATA
pyros_discovery-1.1.1.dist-info/WHEEL
pyros_discovery-1.1.1.dist-info/top_level.txt
pyros_discovery-1.1.1.dist-info/RECORD
