Metadata-Version: 2.1
Name: pyros-discovery
Version: 1.1.1
Summary: Simple discovery service for PyROS
Home-page: https://github.com/Abstract-Horizon/pyros-discovery
Author: Daniel Sendula
License: UNKNOWN
Platform: UNKNOWN
Classifier: Programming Language :: Python :: 3
Classifier: License :: OSI Approved :: Apache Software License
Classifier: Operating System :: OS Independent
Requires-Python: >=3.6
License-File: LICENSE
